completable_html_xblock/__init__.py
completable_html_xblock/html.py
completable_html_xblock/static/js/html_completion.js
completable_html_xblock/translations/README.txt
completable_html_xblock-2.0.0.dist-info/LICENSE
completable_html_xblock-2.0.0.dist-info/METADATA
completable_html_xblock-2.0.0.dist-info/WHEEL
completable_html_xblock-2.0.0.dist-info/entry_points.txt
completable_html_xblock-2.0.0.dist-info/top_level.txt
completable_html_xblock-2.0.0.dist-info/RECORD
