Metadata-Version: 2.2
Name: completable-html-xblock
Version: 2.0.0
Summary: A custom HTML XBlock that can only be marked as completed by calling a custom completion endpoint.
Home-page: https://github.com/open-craft/xblock-html-completable
Author: OpenCraft
License: AGPL v3
Keywords: Python edx
Requires-Python: >=3.11
License-File: LICENSE
Requires-Dist: html-xblock
Dynamic: author
Dynamic: description
Dynamic: description-content-type
Dynamic: home-page
Dynamic: keywords
Dynamic: license
Dynamic: requires-dist
Dynamic: requires-python
Dynamic: summary
